xaal/__init__.py
xaal/tools/__init__.py
xaal/tools/keygen.py
xaal/tools/toolbox.py
xaal/tools/uuidgen.py
xaal_tools-0.7.1.dist-info/METADATA
xaal_tools-0.7.1.dist-info/WHEEL
xaal_tools-0.7.1.dist-info/entry_points.txt
xaal_tools-0.7.1.dist-info/top_level.txt
xaal_tools-0.7.1.dist-info/RECORD
